setup.py
django_pyfixture/__init__.py
django_pyfixture/django_pyfixture.py
django_pyfixture/models.py
django_pyfixture.egg-info/PKG-INFO
django_pyfixture.egg-info/SOURCES.txt
django_pyfixture.egg-info/dependency_links.txt
django_pyfixture.egg-info/not-zip-safe
django_pyfixture.egg-info/top_level.txt