Metadata-Version: 1.0
Name: django-pyfixture
Version: 0.0.2
Summary: Django-PyFixture lets you write fixtures as regular .py-files.
Home-page: https://bitbucket.org/k_bx/django-pyfixture
Author: Konstantine Rybnikov
Author-email: k-bx@k-bx.com
License: BSD
Platform: UNKNOWN
